simple_homepage/__init__.py
simple_homepage/cli.py
simple_homepage/directory_builder.py
simple_homepage/files/settings.yaml
simple_homepage/files/template/_homepage.html
simple_homepage/files/template/static/_stylesheet.css
simple_homepage/files/template/static/favicon.svg
simple_homepage/files/template/static/homepage.js
simple_homepage/files/template/static/images/placeholder_black.png
simple_homepage/files/template/static/images/placeholder_white.png
simple_homepage/homepage_generator.py
simple_homepage-0.0.6.dist-info/entry_points.txt
simple_homepage-0.0.6.dist-info/LICENSE
simple_homepage-0.0.6.dist-info/WHEEL
simple_homepage-0.0.6.dist-info/METADATA
simple_homepage-0.0.6.dist-info/RECORD
