Metadata-Version: 2.1
Name: simple-homepage
Version: 0.0.6
Summary: Command line utility that helps you create a simple static homepage for your browser
Home-page: https://github.com/fpgmaas/simple-homepage
Author: Florian Maas
Author-email: fpgmaas@gmail.com
Requires-Python: >=3.8,<3.11
Classifier: Programming Language :: Python :: 3
Classifier: Programming Language :: Python :: 3.10
Classifier: Programming Language :: Python :: 3.8
Classifier: Programming Language :: Python :: 3.9
Requires-Dist: Jinja2 (>=3.1.2,<4.0.0)
Requires-Dist: PyYAML (>=6.0,<7.0)
Requires-Dist: oyaml (>=1.0,<2.0)
Project-URL: Documentation, https://fpgmaas.github.io/simple-homepage/
Project-URL: Repository, https://github.com/fpgmaas/simple-homepage
